image_to_minecraft/__init__.py
image_to_minecraft/block_to_color.py
image_to_minecraft/blocks.json
image_to_minecraft/image_pixelifier.py
image_to_minecraft/minecraftifier.py
image_to_minecraft/blocks/acacia_leaves.png
image_to_minecraft/blocks/acacia_log.png
image_to_minecraft/blocks/acacia_log_top.png
image_to_minecraft/blocks/acacia_planks.png
image_to_minecraft/blocks/acacia_trapdoor.png
image_to_minecraft/blocks/amethyst_block.png
image_to_minecraft/blocks/amethyst_cluster.png
image_to_minecraft/blocks/ancient_debris_side.png
image_to_minecraft/blocks/ancient_debris_top.png
image_to_minecraft/blocks/andesite.png
image_to_minecraft/blocks/anvil.png
image_to_minecraft/blocks/azalea_leaves.png
image_to_minecraft/blocks/azalea_top.png
image_to_minecraft/blocks/bamboo_block.png
image_to_minecraft/blocks/bamboo_block_top.png
image_to_minecraft/blocks/bamboo_door_bottom.png
image_to_minecraft/blocks/bamboo_fence_gate_particle.png
image_to_minecraft/blocks/bamboo_fence_particle.png
image_to_minecraft/blocks/bamboo_mosaic.png
image_to_minecraft/blocks/bamboo_planks.png
image_to_minecraft/blocks/bamboo_stalk.png
image_to_minecraft/blocks/bamboo_trapdoor.png
image_to_minecraft/blocks/barrel_bottom.png
image_to_minecraft/blocks/barrel_side.png
image_to_minecraft/blocks/barrel_top.png
image_to_minecraft/blocks/basalt_side.png
image_to_minecraft/blocks/basalt_top.png
image_to_minecraft/blocks/beacon.png
image_to_minecraft/blocks/bedrock.png
image_to_minecraft/blocks/bee_nest_bottom.png
image_to_minecraft/blocks/bee_nest_front.png
image_to_minecraft/blocks/bee_nest_front_honey.png
image_to_minecraft/blocks/bee_nest_side.png
image_to_minecraft/blocks/bee_nest_top.png
image_to_minecraft/blocks/beehive_end.png
image_to_minecraft/blocks/beehive_front.png
image_to_minecraft/blocks/beehive_front_honey.png
image_to_minecraft/blocks/beehive_side.png
image_to_minecraft/blocks/birch_leaves.png
image_to_minecraft/blocks/birch_log.png
image_to_minecraft/blocks/birch_log_top.png
image_to_minecraft-0.1.1.dist-info/METADATA
image_to_minecraft-0.1.1.dist-info/WHEEL
image_to_minecraft-0.1.1.dist-info/top_level.txt
image_to_minecraft-0.1.1.dist-info/RECORD
