Metadata-Version: 2.4
Name: image-to-minecraft
Version: 0.1.1
Summary: Takes an image and recreates it from a set of given blocks
Author-email: Nikita Gamygin <nikita.gamygin@gmail.com>
License-Expression: MIT
Classifier: Programming Language :: Python :: 3
Classifier: Operating System :: OS Independent
Requires-Python: >=3.9
Requires-Dist: pillow>=12.0.0
Requires-Dist: numpy>=2.0.0
